jsonparse/VERSION
jsonparse/__init__.py
jsonparse/cli.py
jsonparse/functions.py
jsonparse/parser.py
jsonparse/version.py
jsonparse/webapi.py
jsonparse/static/openapi.yaml
jsonparse/static/css/index.css
jsonparse/static/css/swagger-ui.css
jsonparse/static/img/favicon-16x16.png
jsonparse/static/img/favicon-32x32.png
jsonparse/static/js/swagger-initializer.js
jsonparse/static/js/swagger-ui-bundle.js
jsonparse/static/js/swagger-ui-es-bundle-core.js
jsonparse/static/js/swagger-ui-es-bundle.js
jsonparse/static/js/swagger-ui-standalone-preset.js
jsonparse/static/js/swagger-ui.js
jsonparse/templates/index.html
jsonparse/templates/swaggerui.html
jsonparse-0.15.1.dist-info/METADATA
jsonparse-0.15.1.dist-info/WHEEL
jsonparse-0.15.1.dist-info/entry_points.txt
jsonparse-0.15.1.dist-info/licenses/LICENSE
jsonparse-0.15.1.dist-info/RECORD
