Metadata-Version: 2.1
Name: jsonparse
Version: 0.15.1
Summary: ctrl-f for JSON. A simple JSON parsing library. Extract what's needed from key:value pairs.
Project-URL: Documentation, https://jsonparse.readthedocs.io/en/latest/
Project-URL: Source code, https://github.com/ctomkow/jsonparse
Author-email: Craig Abt Tomkow <ctomkow@gmail.com>
Maintainer-email: Craig Abt Tomkow <ctomkow@gmail.com>
License-File: LICENSE
Keywords: JSON,filter,key value,parse,parsing,python,search,searching
Classifier: Development Status :: 3 - Alpha
Classifier: License :: OSI Approved :: MIT License
Classifier: Natural Language :: English
Classifier: Operating System :: OS Independent
Classifier: Programming Language :: Python :: 2.7
Classifier: Programming Language :: Python :: 3.6
Classifier: Programming Language :: Python :: 3.7
Classifier: Programming Language :: Python :: 3.8
Classifier: Programming Language :: Python :: 3.9
Classifier: Programming Language :: Python :: 3.10
Classifier: Programming Language :: Python :: 3.11
Classifier: Programming Language :: Python :: 3.12
Classifier: Programming Language :: Python :: 3.13
Requires-Python: !=3.0,!=3.1,!=3.2,!=3.3,!=3.4,!=3.5,>=2.7
Provides-Extra: buildtest27
Requires-Dist: hatchling==0.25.1; extra == 'buildtest27'
Requires-Dist: pytest-cov==2.12.1; extra == 'buildtest27'
Requires-Dist: pytest==4.6.11; extra == 'buildtest27'
Provides-Extra: buildtest37-onward
Requires-Dist: flake8>=5.0.0; extra == 'buildtest37-onward'
Requires-Dist: flask==2.0.3; extra == 'buildtest37-onward'
Requires-Dist: gunicorn==20.1.0; extra == 'buildtest37-onward'
Requires-Dist: hatchling==1.17.1; extra == 'buildtest37-onward'
Requires-Dist: pytest-cov<3.0.0,>=2.6.1; extra == 'buildtest37-onward'
Requires-Dist: pytest==7.0.1; extra == 'buildtest37-onward'
Requires-Dist: werkzeug==2.0.0; extra == 'buildtest37-onward'
Provides-Extra: dev
Requires-Dist: flake8>=5.0.0; extra == 'dev'
Requires-Dist: flask==2.0.3; extra == 'dev'
Requires-Dist: gunicorn==20.1.0; extra == 'dev'
Requires-Dist: hatchling==1.17.1; extra == 'dev'
Requires-Dist: pytest-cov<3.0.0,>=2.6.1; extra == 'dev'
Requires-Dist: pytest==7.0.1; extra == 'dev'
Requires-Dist: werkzeug==2.0.0; extra == 'dev'
Provides-Extra: webapi
Requires-Dist: flask==2.0.3; extra == 'webapi'
Requires-Dist: gunicorn==20.1.0; extra == 'webapi'
Requires-Dist: werkzeug==2.0.0; extra == 'webapi'
